MANIFEST.in
README.rst
setup.py
django_easytests.egg-info/PKG-INFO
django_easytests.egg-info/SOURCES.txt
django_easytests.egg-info/dependency_links.txt
django_easytests.egg-info/not-zip-safe
django_easytests.egg-info/requires.txt
django_easytests.egg-info/top_level.txt
djeasytests/__init__.py
djeasytests/runners.py
djeasytests/testsetup.py
djeasytests/tmpdir.py