Metadata-Version: 1.1
Name: django-easytests
Version: 0.9.4
Summary: Modified test utils from django-cms as a own module
Home-page: http://github.com/fivethreeo/django-easytests/
Author: Oyvind Saltvik
Author-email: oyvind.saltvik@gmail.com
License: UNKNOWN
Platform: UNKNOWN
Classifier: Development Status :: 4 - Beta
Classifier: Environment :: Web Environment
Classifier: Intended Audience :: Developers
Classifier: License :: OSI Approved :: BSD License
Classifier: Operating System :: OS Independent
Classifier: Programming Language :: Python
Classifier: Framework :: Django
